spec_cli/__init__.py
spec_cli/__main__.py
spec_cli/cli/__init__.py
spec_cli/cli/app.py
spec_cli/cli/commands/__init__.py
spec_cli/cli/commands/add.py
spec_cli/cli/commands/commit.py
spec_cli/cli/commands/diff.py
spec_cli/cli/commands/gen.py
spec_cli/cli/commands/generation/__init__.py
spec_cli/cli/commands/generation/prompts.py
spec_cli/cli/commands/generation/validation.py
spec_cli/cli/commands/generation/workflows.py
spec_cli/cli/commands/help.py
spec_cli/cli/commands/history/__init__.py
spec_cli/cli/commands/history/content_viewer.py
spec_cli/cli/commands/history/diff_viewer.py
spec_cli/cli/commands/history/formatters.py
spec_cli/cli/commands/init.py
spec_cli/cli/commands/log.py
spec_cli/cli/commands/regen.py
spec_cli/cli/commands/show.py
spec_cli/cli/commands/status.py
spec_cli/cli/exceptions.py
spec_cli/cli/options.py
spec_cli/cli/utils.py
spec_cli/config/__init__.py
spec_cli/config/loader.py
spec_cli/config/settings.py
spec_cli/config/validation.py
spec_cli/core/__init__.py
spec_cli/core/commit_manager.py
spec_cli/core/repository_init.py
spec_cli/core/repository_state.py
spec_cli/core/workflow_orchestrator.py
spec_cli/core/workflow_state.py
spec_cli/exceptions.py
spec_cli/file_processing/__init__.py
spec_cli/file_processing/batch_processor.py
spec_cli/file_processing/change_detector.py
spec_cli/file_processing/conflict_resolver.py
spec_cli/file_processing/file_cache.py
spec_cli/file_processing/merge_helpers.py
spec_cli/file_processing/processing_pipeline.py
spec_cli/file_processing/progress_events.py
spec_cli/file_system/__init__.py
spec_cli/file_system/directory_manager.py
spec_cli/file_system/directory_traversal.py
spec_cli/file_system/file_metadata.py
spec_cli/file_system/file_type_detector.py
spec_cli/file_system/file_utils.py
spec_cli/file_system/ignore_patterns.py
spec_cli/file_system/path_resolver.py
spec_cli/file_system/path_utils.py
spec_cli/git/__init__.py
spec_cli/git/operations.py
spec_cli/git/path_converter.py
spec_cli/git/repository.py
spec_ai-0.1.51.dist-info/METADATA
spec_ai-0.1.51.dist-info/WHEEL
spec_ai-0.1.51.dist-info/entry_points.txt
spec_ai-0.1.51.dist-info/RECORD
