Metadata-Version: 2.3
Name: spec-ai
Version: 0.1.51
Summary: A versioned documentation layer for AI-assisted development
License: MIT
Keywords: documentation,ai,development,git
Author: Spenser McConnell
Author-email: spensermcconnell@gmail.com
Requires-Python: >=3.8,<4.0
Classifier: Development Status :: 3 - Alpha
Classifier: Intended Audience :: Developers
Classifier: License :: OSI Approved :: MIT License
Classifier: Programming Language :: Python :: 3
Classifier: Programming Language :: Python :: 3.8
Classifier: Programming Language :: Python :: 3.9
Classifier: Programming Language :: Python :: 3.10
Classifier: Programming Language :: Python :: 3.11
Classifier: Programming Language :: Python :: 3.12
Classifier: Programming Language :: Python :: 3.13
Classifier: Topic :: Software Development :: Documentation
Classifier: Topic :: Software Development :: Version Control :: Git
Requires-Dist: click (>=8.1.7,<9.0.0)
Requires-Dist: pydantic (>=2.5.0,<3.0.0)
Requires-Dist: pyyaml (>=6.0.1,<7.0.0)
Requires-Dist: rich (>=14.0.0,<15.0.0)
Requires-Dist: rich-click (>=1.7.1,<2.0.0)
Requires-Dist: tenacity (>=8.2.3,<9.0.0)
Requires-Dist: tomli (>=2.2.1,<3.0.0)
Project-URL: Homepage, https://github.com/Spenquatch/spec
Project-URL: Repository, https://github.com/Spenquatch/spec
